{"holdType":"TITLE","status":"PLACED","pickupLibrary":"HWD","item":"1485513:19:2","bib":"1485513","title":"The vanishing half","author":"Bennett, Brit,","callNumber":"FICTION BENNETT 2020","sortCallNumber":"FICTION BENNETT 2020","barcode":"31168131218479","currentLocation":"A-F","locationDescription":"General fiction","itemType":"BOOK"}
{"holdType":"TITLE","status":"PLACED","pickupLibrary":"GRG","item":"605714:20:1","bib":"605714","title":"My sister, the serial killer : a novel","author":"Braithwaite, Oyinkan,","callNumber":"FICTION BRAITHWAI 2018","sortCallNumber":"FICTION BRAITHWAI 2018","barcode":"31168127474755","currentLocation":"A-F","locationDescription":"General fiction","itemType":"BOOK"}
{"holdType":"TITLE","status":"PLACED","pickupLibrary":"MAIL","item":"255314:20:1","bib":"255314","title":"Late in the day : a novel","author":"Hadley, Tessa,","callNumber":"FICTION HADLEY 2019","sortCallNumber":"FICTION HADLEY 2019","barcode":"31168127540373","currentLocation":"A-F","locationDescription":"General fiction","itemType":"BOOK"}
{"holdType":"TITLE","status":"PLACED","pickupLibrary":"MID","item":"668682:17:1","bib":"668682","title":"The wife between us","author":"Hendricks, Greer,","callNumber":"FICTION HENDRICKS 2018","sortCallNumber":"FICTION HENDRICKS 2018","barcode":"31168120990559","currentLocation":"A-F","locationDescription":"General fiction","itemType":"BOOK"}
{"holdType":"TITLE","status":"PLACED","pickupLibrary":"BMT","item":"811731:5:1","bib":"811731","title":"The blazing world : a novel","author":"Hustvedt, Siri.","callNumber":"FICTION HUSTVEDT 2014","sortCallNumber":"FICTION HUSTVEDT 2014","barcode":"31168112202575","currentLocation":"A-F","locationDescription":"General fiction","itemType":"BOOK"}
{"holdType":"TITLE","status":"PLACED","pickupLibrary":"HWD","item":"81284:19:1","bib":"81284","title":"The road","author":"McCarthy, Cormac, 1933-","callNumber":"FICTION MCCARTHY 2006","sortCallNumber":"FICTION MCCARTHY 2006","barcode":"31168125929842","currentLocation":"A-F","locationDescription":"General fiction","itemType":"BOOK"}
{"holdType":"TITLE","status":"PLACED","pickupLibrary":"BMT","item":"1744003:7:1","bib":"1744003","title":"The invisible woman","author":"Robuck, Erika,","callNumber":"FICTION ROBUCK 2021","sortCallNumber":"FICTION ROBUCK 2021","barcode":"31168127199410","currentLocation":"A-F","locationDescription":"General fiction","itemType":"BOOK"}
{"holdType":"TITLE","status":"PLACED","pickupLibrary":"HDL","item":"1733014:15:1","bib":"1733014","title":"The devil may dance : a novel","author":"Tapper, Jake,","callNumber":"FICTION TAPPER 2021","sortCallNumber":"FICTION TAPPER 2021","barcode":"31168133964823","currentLocation":"A-F","locationDescription":"General fiction","itemType":"BOOK"}
{"holdType":"TITLE","status":"PLACED","pickupLibrary":"BMT","item":"772001:22:1","bib":"772001","title":"B.J. Thomas greatest hits","author":"Thomas, B. J.","callNumber":"CD Popular THOMAS","sortCallNumber":"CD POPULAR THOMAS","barcode":"31168108319904","currentLocation":"A-M-C","locationDescription":"Music CDs","itemType":"ADISC-F"}
{"holdType":"TITLE","status":"PLACED","pickupLibrary":"NRW","item":"82483:18:1","bib":"82483","title":"Practical magic : a beginner's guide to crystals, horoscopes, psychics & spells","author":"Van De Car, Nikki,","callNumber":"133.43 V225p 2017","sortCallNumber":"133.43 V225P 2017","barcode":"31168122031337","currentLocation":"A-N","locationDescription":"Nonfiction","itemType":"BOOK"}
{"holdType":"TITLE","status":"PLACED","pickupLibrary":"GRG","item":"1899325:18:1","bib":"1899325","title":"The premonitions bureau : a true account of death foretold","author":"Knight, Sam (Investigative reporter),","callNumber":"133.86094 K713p 2022","sortCallNumber":"133.86094 K713P 2022","barcode":"31168135324612","currentLocation":"A-N","locationDescription":"Nonfiction","itemType":"BOOK"}
{"holdType":"TITLE","status":"PLACED","pickupLibrary":"HWD","item":"1344027:5:1","bib":"1344027","title":"The healing power of plants : the hero house plants that will love you back","author":"Bailey, Fran,","callNumber":"635.965 B1546h 2019","sortCallNumber":"635.965 B1546H 2019","barcode":"31168125790020","currentLocation":"A-N","locationDescription":"Nonfiction","itemType":"BOOK"}
{"holdType":"TITLE","status":"PLACED","pickupLibrary":"STJ","item":"1899501:3:1","bib":"1899501","title":"Make no small plans : lessons on thinking big, chasing dreams, and building community","author":"Bisnow, Elliott,","callNumber":"658.4 B6229m 2020","sortCallNumber":"658.4 B6229M 2020","barcode":"31168135315131","currentLocation":"A-N","locationDescription":"Nonfiction","itemType":"BOOK"}
{"holdType":"TITLE","status":"PLACED","pickupLibrary":"HDL","item":"282346:17:1","bib":"282346","title":"Beastie Boys book","author":"Mike D, 1965-","callNumber":"782.42164 M6365b 2018","sortCallNumber":"782.42164 M6365B 2018","barcode":"31168125344125","currentLocation":"A-N","locationDescription":"Nonfiction","itemType":"BOOK"}
{"holdType":"TITLE","status":"PLACED","pickupLibrary":"ROC","item":"380689:6:1","bib":"380689","title":"Basho : the complete haiku","author":"Matsuo, Bash\u014d, 1644-1694.","callNumber":"895.2 M43b 2008","sortCallNumber":"895.2 M43B 2008","barcode":"31168097886178","currentLocation":"A-N","locationDescription":"Nonfiction","itemType":"BOOK"}
{"holdType":"TITLE","status":"PLACED","pickupLibrary":"ALB","item":"1956495:18:1","bib":"1956495","title":"Rick Steves Rome","author":"Steves, Rick, 1955- https:\/\/isni.org\/isni\/0000000083980702.","callNumber":"914.5632 S8489r 2022","sortCallNumber":"914.5632 S8489R 2022","barcode":"31168136003405","currentLocation":"A-N","locationDescription":"Nonfiction","itemType":"BOOK"}
{"holdType":"TITLE","status":"PLACED","pickupLibrary":"HGT","item":"992398:18:1","bib":"992398","title":"Dear America : notes of an undocumented citizen","author":"Vargas, Jose Antonio,","callNumber":"BIO 304.873 VARGAS 2018","sortCallNumber":"BIO 304.873 VARGAS 2018","barcode":"31168127617841","currentLocation":"A-N-B","locationDescription":"Biography","itemType":"BOOK"}
{"holdType":"TITLE","status":"PLACED","pickupLibrary":"ALB","item":"278200:7:1","bib":"278200","title":"The honey bus : a memoir of loss, courage and a girl saved by bees","author":"May, Meredith,","callNumber":"BIO 638.1 MAY 2019","sortCallNumber":"BIO 638.1 MAY 2019","barcode":"31168127728887","currentLocation":"A-N-B","locationDescription":"Biography","itemType":"BOOK"}
{"holdType":"TITLE","status":"PLACED","pickupLibrary":"NRW","item":"412280:20:1","bib":"412280","title":"1 big salad","author":"Medina, Juana, 1980-","callNumber":"jE Concept MEDINA 2016","sortCallNumber":"JE CONCEPT MEDINA 2016","barcode":"31168130575978","currentLocation":"J-E-C","locationDescription":"Concept books","itemType":"BOOK-J"}
{"holdType":"TITLE","status":"PLACED","pickupLibrary":"SEL","item":"1841994:12:1","bib":"1841994","title":"Sato the rabbit","author":"Ainoya, Yuki,","callNumber":"jE AINOYA 2021","sortCallNumber":"JE AINOYA 2021","barcode":"31168134961398","currentLocation":"J-E-E","locationDescription":"Picture books","itemType":"BOOK-J"}
{"holdType":"TITLE","status":"PLACED","pickupLibrary":"SEL","item":"774936:12:1","bib":"774936","title":"Lena's shoes are nervous : a first-day-of-school dilemma","author":"Calabrese, Keith,","callNumber":"jE CALABRESE 2018","sortCallNumber":"JE CALABRESE 2018","barcode":"31168126628385","currentLocation":"J-E-E","locationDescription":"Picture books","itemType":"BOOK-J"}
{"holdType":"TITLE","status":"PLACED","pickupLibrary":"HWD","item":"1698714:18:1","bib":"1698714","title":"Llama Llama loose tooth drama","author":"Dewdney, Anna,","callNumber":"jE DEWDNEY 2020","sortCallNumber":"JE DEWDNEY 2020","barcode":"31168131143370","currentLocation":"J-E-E","locationDescription":"Picture books","itemType":"BOOK-J"}
{"holdType":"TITLE","status":"PLACED","pickupLibrary":"HDL","item":"709388:10:1","bib":"709388","title":"Picture day perfection","author":"Diesen, Deborah.","callNumber":"jE DIESEN 2013","sortCallNumber":"JE DIESEN 2013","barcode":"31168110841259","currentLocation":"J-E-E","locationDescription":"Picture books","itemType":"BOOK-J"}
{"holdType":"TITLE","status":"PLACED","pickupLibrary":"WOD","item":"1492212:18:1","bib":"1492212","title":"Don't worry, little crab","author":"Haughton, Chris,","callNumber":"jE HAUGHTON 2020","sortCallNumber":"JE HAUGHTON 2020","barcode":"31168130996547","currentLocation":"J-E-E","locationDescription":"Picture books","itemType":"BOOK-J"}
{"holdType":"TITLE","status":"PLACED","pickupLibrary":"WOD","item":"1803253:18:1","bib":"1803253","title":"El Cucuy is scared, too!","author":"Higuera, Donna Barba,","callNumber":"jE HIGUERA 2021","sortCallNumber":"JE HIGUERA 2021","barcode":"31168133870251","currentLocation":"J-E-E","locationDescription":"Picture books","itemType":"BOOK-J"}
{"holdType":"TITLE","status":"PLACED","pickupLibrary":"HGT","item":"1320018:14:1","bib":"1320018","title":"Flora and the flamingo","author":"Idle, Molly Schaar,","callNumber":"jE IDLE 2013","sortCallNumber":"JE IDLE 2013","barcode":"31168120965387","currentLocation":"J-E-E","locationDescription":"Picture books","itemType":"BOOK-J"}
{"holdType":"TITLE","status":"PLACED","pickupLibrary":"BMT","item":"859828:18:1","bib":"859828","title":"The very last castle","author":"Jonker, Travis,","callNumber":"jE JONKER 2018","sortCallNumber":"JE JONKER 2018","barcode":"31168126667706","currentLocation":"J-E-E","locationDescription":"Picture books","itemType":"BOOK-J"}
{"holdType":"TITLE","status":"PLACED","pickupLibrary":"CAP","item":"1874622:12:1","bib":"1874622","title":"The song of the nightingale","author":"Landman, Tanya,","callNumber":"jE LANDMAN 2022","sortCallNumber":"JE LANDMAN 2022","barcode":"31168135174694","currentLocation":"J-E-E","locationDescription":"Picture books","itemType":"BOOK-J"}
{"holdType":"TITLE","status":"PLACED","pickupLibrary":"HDL","item":"1347304:18:1","bib":"1347304","title":"Froggy picks a pumpkin","author":"London, Jonathan, 1947-","callNumber":"jE LONDON 2019","sortCallNumber":"JE LONDON 2019","barcode":"31168130797812","currentLocation":"J-E-E","locationDescription":"Picture books","itemType":"BOOK-J"}
{"holdType":"TITLE","status":"PLACED","pickupLibrary":"HDL","item":"1962162:12:1","bib":"1962162","title":"Sometimes love","author":"Moore, Katrina,","callNumber":"jE MOORE 2022","sortCallNumber":"JE MOORE 2022","barcode":"31168135284659","currentLocation":"J-E-E","locationDescription":"Picture books","itemType":"BOOK-J"}
{"holdType":"TITLE","status":"PLACED","pickupLibrary":"HGT","item":"1343787:18:1","bib":"1343787","title":"Mermaid dreams","author":"Pugsley, Kate,","callNumber":"jE PUGSLEY 2019","sortCallNumber":"JE PUGSLEY 2019","barcode":"31168130610973","currentLocation":"J-E-E","locationDescription":"Picture books","itemType":"BOOK-J"}
{"holdType":"TITLE","status":"PLACED","pickupLibrary":"MID","item":"1771498:18:1","bib":"1771498","title":"Mi casa is my home","author":"Sala, Laurenne,","callNumber":"jE SALA 2021","sortCallNumber":"JE SALA 2021","barcode":"31168133963866","currentLocation":"J-E-E","locationDescription":"Picture books","itemType":"BOOK-J"}
{"holdType":"TITLE","status":"PLACED","pickupLibrary":"STJ","item":"871542:11:1","bib":"871542","title":"The sea tiger","author":"Turnbull, Victoria,","callNumber":"jE TURNBULL 2015","sortCallNumber":"JE TURNBULL 2015","barcode":"31168115661223","currentLocation":"J-E-E","locationDescription":"Picture books","itemType":"BOOK-J"}
{"holdType":"TITLE","status":"PLACED","pickupLibrary":"CAP","item":"1742724:7:1","bib":"1742724","title":"Small room, big dreams : the journey of Juli\u00e1n and Joaquin Castro","author":"Brown, Monica, 1969-","callNumber":"j BIO Facts 324.2 CASTRO 2021","sortCallNumber":"J BIO FACTS 324.2  CASTRO 2021","barcode":"31168133781904","currentLocation":"J-E-F","locationDescription":"Beginning Facts","itemType":"BOOK-J"}
{"holdType":"TITLE","status":"PLACED","pickupLibrary":"NRW","item":"1723832:12:1","bib":"1723832","title":"When Cloud became a cloud","author":"Hodgson, Rob,","callNumber":"j Facts 551.48 H6917w 2021","sortCallNumber":"J FACTS 551.48  H6917W 2021","barcode":"31168131291948","currentLocation":"J-E-F","locationDescription":"Beginning Facts","itemType":"BOOK-J"}
{"holdType":"TITLE","status":"PLACED","pickupLibrary":"NPO","item":"1090686:17:1","bib":"1090686","title":"I want to be a doctor","author":"Driscoll, Laura,","callNumber":"Blue Reader DRISCOLL 2018","sortCallNumber":"BLUE READER DRISCOLL 2018","barcode":"31168121226086","currentLocation":"J-E-R","locationDescription":"Easy Readers","itemType":"BOOK-J"}
{"holdType":"TITLE","status":"PLACED","pickupLibrary":"ALB","item":"1915465:18:1","bib":"1915465","title":"The uncommon cold","author":"Messinger, Jonathan,","callNumber":"Green Reader MESSINGER 2021","sortCallNumber":"GREEN READER MESSINGER 2021","barcode":"31168135392346","currentLocation":"J-E-R","locationDescription":"Easy Readers","itemType":"BOOK-J"}
{"holdType":"TITLE","status":"PLACED","pickupLibrary":"HWD","item":"1832952:18:1","bib":"1832952","title":"Catalina incognito","author":"Torres, Jennifer, 1980-","callNumber":"Green Reader TORRES 2022","sortCallNumber":"GREEN READER TORRES 2022","barcode":"31168135126298","currentLocation":"J-E-R","locationDescription":"Easy Readers","itemType":"BOOK-J"}
{"holdType":"TITLE","status":"PLACED","pickupLibrary":"HGT","item":"1027015:18:1","bib":"1027015","title":"Roar of the thunder dragon","author":"West, Tracey, 1965-","callNumber":"Green Reader WEST 2017","sortCallNumber":"GREEN READER WEST 2017","barcode":"31168121946220","currentLocation":"J-E-R","locationDescription":"Easy Readers","itemType":"BOOK-J"}
{"holdType":"TITLE","status":"PLACED","pickupLibrary":"WOD","item":"113316:18:1","bib":"113316","title":"King & Kayla and the case of the secret code","author":"Butler, Dori Hillestad,","callNumber":"Red Reader BUTLER 2017","sortCallNumber":"RED READER BUTLER 2017","barcode":"31168116152933","currentLocation":"J-E-R","locationDescription":"Easy Readers","itemType":"BOOK-J"}
{"holdType":"TITLE","status":"PLACED","pickupLibrary":"HGT","item":"114988:18:1","bib":"114988","title":"Meet Yasmin!","author":"Faruqi, Saadia,","callNumber":"Red Reader FARUQI 2018","sortCallNumber":"RED READER FARUQI 2018","barcode":"31168125503019","currentLocation":"J-E-R","locationDescription":"Easy Readers","itemType":"BOOK-J"}
{"holdType":"TITLE","status":"PLACED","pickupLibrary":"HWD","item":"1925280:18:1","bib":"1925280","title":"Emily's big discovery","author":"Kessler, Liz,","callNumber":"Red Reader KESSLER 2022","sortCallNumber":"RED READER KESSLER 2022","barcode":"31168135373882","currentLocation":"J-E-R","locationDescription":"Easy Readers","itemType":"BOOK-J"}
{"holdType":"TITLE","status":"PLACED","pickupLibrary":"MID","item":"384311:16:2","bib":"384311","title":"Mr. Putter & Tabby spill the beans","author":"Rylant, Cynthia,","callNumber":"Red Reader RYLANT 2009","sortCallNumber":"RED READER RYLANT 2009","barcode":"31168098753443","currentLocation":"J-E-R","locationDescription":"Easy Readers","itemType":"BOOK-J"}
{"holdType":"TITLE","status":"PLACED","pickupLibrary":"NRW","item":"247232:8:1","bib":"247232","title":"Who's hungry?","author":"Hacohen, Dean,","callNumber":"jE Toddler HACOHEN 2015","sortCallNumber":"JE TODDLER HACOHEN 2015","barcode":"31168117619674","currentLocation":"J-E-T","locationDescription":"Toddler books","itemType":"BOOK-J"}
{"holdType":"TITLE","status":"PLACED","pickupLibrary":"STJ","item":"1004446:20:2","bib":"1004446","title":"The one and only Ivan","author":"Applegate, Katherine,","callNumber":"j APPLEGATE 2012","sortCallNumber":"J APPLEGATE 2012","barcode":"31168124105675","currentLocation":"J-F","locationDescription":"Fiction for kids","itemType":"BOOK-J"}
{"holdType":"TITLE","status":"PLACED","pickupLibrary":"GRG","item":"1857734:11:1","bib":"1857734","title":"Camp Murderface","author":"Berk, Josh,","callNumber":"j BERK 2021","sortCallNumber":"J BERK 2021","barcode":"31168134262540","currentLocation":"J-F","locationDescription":"Fiction for kids","itemType":"BOOK-J"}
{"holdType":"TITLE","status":"PLACED","pickupLibrary":"NRW","item":"1846975:18:1","bib":"1846975","title":"Aru Shah and the nectar of immortality","author":"Chokshi, Roshani,","callNumber":"j CHOKSHI 2022","sortCallNumber":"J CHOKSHI 2022","barcode":"31168135237426","currentLocation":"J-F","locationDescription":"Fiction for kids","itemType":"BOOK-J"}
{"holdType":"TITLE","status":"PLACED","pickupLibrary":"NPO","item":"1951884:12:1","bib":"1951884","title":"Flipping forward twisting backward","author":"Fullerton, Alma,","callNumber":"j FULLERTON 2022","sortCallNumber":"J FULLERTON 2022","barcode":"31168136600168","currentLocation":"J-F","locationDescription":"Fiction for kids","itemType":"BOOK-J"}
{"holdType":"TITLE","status":"PLACED","pickupLibrary":"GRG","item":"620555:16:7","bib":"620555","title":"Diary of a wimpy kid. Greg Heffley's journal","author":"Kinney, Jeff,","callNumber":"j KINNEY","sortCallNumber":"J KINNEY","barcode":"31168128966882","currentLocation":"J-F","locationDescription":"Fiction for kids","itemType":"BOOK-J"}
{"holdType":"TITLE","status":"PLACED","pickupLibrary":"SEL","item":"1026699:9:1","bib":"1026699","title":"Lulu and the rabbit next door","author":"McKay, Hilary.","callNumber":"j MCKAY 2014","sortCallNumber":"J MCKAY 2014","barcode":"31168111914055","currentLocation":"J-F","locationDescription":"Fiction for kids","itemType":"BOOK-J"}
{"holdType":"TITLE","status":"PLACED","pickupLibrary":"CAP","item":"247700:12:1","bib":"247700","title":"Wrath of the storm","author":"Nielsen, Jennifer A.,","callNumber":"j NIELSEN 2017","sortCallNumber":"J NIELSEN 2017","barcode":"31168117563948","currentLocation":"J-F","locationDescription":"Fiction for kids","itemType":"BOOK-J"}
{"holdType":"TITLE","status":"PLACED","pickupLibrary":"HWD","item":"1115943:9:1","bib":"1115943","title":"The Carpet people","author":"Pratchett, Terry.","callNumber":"j PRATCHETT 2013","sortCallNumber":"J PRATCHETT 2013","barcode":"31168108976356","currentLocation":"J-F","locationDescription":"Fiction for kids","itemType":"BOOK-J"}
{"holdType":"TITLE","status":"PLACED","pickupLibrary":"NPO","item":"1520562:18:1","bib":"1520562","title":"They call me the Night Howler!","author":"Stine, R. L.,","callNumber":"j STINE 2020","sortCallNumber":"J STINE 2020","barcode":"31168127285821","currentLocation":"J-F","locationDescription":"Fiction for kids","itemType":"BOOK-J"}
{"holdType":"TITLE","status":"PLACED","pickupLibrary":"GRG","item":"1762533:18:1","bib":"1762533","title":"Paranorthern and the chaos bunny a-hop-calypse","author":"Cooke, Stephanie, 1986-","callNumber":"jgn COOKE 2021","sortCallNumber":"JGN COOKE 2021","barcode":"31168133892255","currentLocation":"J-G-F","locationDescription":"Fiction graphic novels for kids","itemType":"BOOK-J"}
{"holdType":"TITLE","status":"PLACED","pickupLibrary":"NRW","item":"1749989:15:1","bib":"1749989","title":"Real pigeons nest hard","author":"McDonald, Andrew, 1982-","callNumber":"jgn MCDONALD 2020","sortCallNumber":"JGN MCDONALD 2020","barcode":"31168131747170","currentLocation":"J-G-F","locationDescription":"Fiction graphic novels for kids","itemType":"BOOK-J"}
{"holdType":"TITLE","status":"PLACED","pickupLibrary":"HGT","item":"578356:10:1","bib":"578356","title":"Moonlight : the Halloween cat","author":"Rylant, Cynthia.","callNumber":"jE Holiday RYLANT","sortCallNumber":"JE HOLIDAY RYLANT","barcode":"31168069314894","currentLocation":"J-H","locationDescription":"Holiday books","itemType":"BOOK-J-F"}
{"holdType":"TITLE","status":"PLACED","pickupLibrary":"FRV","item":"908268:16:1","bib":"908268","title":"Unicorns","author":"Peabody, Erin,","callNumber":"j 398.2454 P351u 2018","sortCallNumber":"J 398.2454 P351U 2018","barcode":"31168121084527","currentLocation":"J-N","locationDescription":"Nonfiction for kids","itemType":"BOOK-J"}
{"holdType":"TITLE","status":"PLACED","pickupLibrary":"NRW","item":"116453:14:1","bib":"116453","title":"Lift every voice and sing : a celebration of the African American national anthem","author":"Johnson, James Weldon, 1871-1938,","callNumber":"j 782.42164 J675L 2019","sortCallNumber":"J 782.42164 J675L 2019","barcode":"31168127523205","currentLocation":"J-N","locationDescription":"Nonfiction for kids","itemType":"BOOK-J"}
{"holdType":"TITLE","status":"PLACED","pickupLibrary":"CAP","item":"1963063:12:1","bib":"1963063","title":"Roberto Clemente","author":"Romo Edelman, Claudia,","callNumber":"j BIO 796.357 CLEMENTE 2022","sortCallNumber":"J BIO 796.357  CLEMENTE 2022","barcode":"31168135513701","currentLocation":"J-N","locationDescription":"Nonfiction for kids","itemType":"BOOK-J"}
{"holdType":"TITLE","status":"PLACED","pickupLibrary":"HDL","item":"904857:6:1","bib":"904857","title":"The big, big wall","author":"Howard, Reginald.","callNumber":"SPANISH Amarillo Lector HOWARD 2009","sortCallNumber":"SPANISH AMARILLO LECTOR HOWARD 2009","barcode":"31168108750520","currentLocation":"J-W-R","locationDescription":"Spanish Readers","itemType":"BOOK-J"}
{"holdType":"TITLE","status":"PLACED","pickupLibrary":"HDL","item":"1292829:8:1","bib":"1292829","title":"Perrazo y Perrito = Big Dog and Little Dog","author":"Pilkey, Dav, 1966-","callNumber":"SPANISH Amarillo Lector PILKEY 2016","sortCallNumber":"SPANISH AMARILLO LECTOR PILKEY 2016","barcode":"31168122411497","currentLocation":"J-W-R","locationDescription":"Spanish Readers","itemType":"BOOK-J"}
{"holdType":"TITLE","status":"PLACED","pickupLibrary":"HDL","item":"798137:7:1","bib":"798137","title":"Jorge el curioso se divierte haciendo gimnasia = Curious George Gymnastics fun","author":"Bernstein, Leora,","callNumber":"SPANISH Azul Lector BERNSTEIN 2015","sortCallNumber":"SPANISH AZUL LECTOR BERNSTEIN 2015","barcode":"31168116488535","currentLocation":"J-W-R","locationDescription":"Spanish Readers","itemType":"BOOK-J"}
{"holdType":"TITLE","status":"PLACED","pickupLibrary":"HDL","item":"1097792:7:1","bib":"1097792","title":"Jorge el curioso : el baile","author":"Greku, Borana,","callNumber":"SPANISH Azul Lector GREKU 2013","sortCallNumber":"SPANISH AZUL LECTOR GREKU 2013","barcode":"31168116457589","currentLocation":"J-W-R","locationDescription":"Spanish Readers","itemType":"BOOK-J"}
